Reddit_ChatBot_Python/__init__.py
Reddit_ChatBot_Python/_events.py
Reddit_ChatBot_Python/_ws_client.py
Reddit_ChatBot_Python/chatbot.py
Reddit_ChatBot_Python/reddit_auth.py
Reddit_ChatBot_Python/_api/iconkeys.py
Reddit_ChatBot_Python/_api/models.py
Reddit_ChatBot_Python/_api/tools.py
Reddit_ChatBot_Python/_utils/consts.py
Reddit_ChatBot_Python/_utils/exceptions.py
Reddit_ChatBot_Python/_utils/frame_model.py
Reddit_ChatBot_Python/_utils/ws_utils.py
Reddit_ChatBot_Python-1.4.9.dist-info/LICENSE
Reddit_ChatBot_Python-1.4.9.dist-info/METADATA
Reddit_ChatBot_Python-1.4.9.dist-info/WHEEL
Reddit_ChatBot_Python-1.4.9.dist-info/top_level.txt
Reddit_ChatBot_Python-1.4.9.dist-info/RECORD
