Metadata-Version: 2.1
Name: Reddit-ChatBot-Python
Version: 1.4.9
Summary: an event-driven chatbot library for reddit chatrooms
Home-page: https://github.com/scrubjay55/Reddit_ChatBot_Python.git
Author: scrubjay55
License: APLv2
Project-URL: Source, https://github.com/scrubjay55/Reddit_ChatBot_Python.git
Platform: UNKNOWN
Classifier: Operating System :: OS Independent
Classifier: Programming Language :: Python
Classifier: Programming Language :: Python :: 3.6
Classifier: Programming Language :: Python :: 3.7
Classifier: Programming Language :: Python :: 3.8
Classifier: Programming Language :: Python :: 3.9
Classifier: Programming Language :: Python :: 3.10
Requires-Python: >=3.6
License-File: LICENSE
